jieba_next-1.0.0a5.dist-info/RECORD
jieba_next-1.0.0a5.dist-info/WHEEL
jieba_next-1.0.0a5.dist-info/entry_points.txt
jieba_next-1.0.0a5.dist-info/top_level.txt
jieba_next-1.0.0a5.dist-info/METADATA
jieba_next-1.0.0a5.dist-info/licenses/LICENSE
jieba_next/_version.py
jieba_next/lib.rs
jieba_next/__init__.py
jieba_next/jieba_next_rust.cpython-310-darwin.so
jieba_next/__main__.py
jieba_next/dict.txt
jieba_next/analyse/textrank.py
jieba_next/analyse/analyzer.py
jieba_next/analyse/__init__.py
jieba_next/analyse/idf.txt
jieba_next/analyse/tfidf.py
jieba_next/posseg/prob_trans.py
jieba_next/posseg/prob_emit.py
jieba_next/posseg/__init__.py
jieba_next/posseg/prob_start.py
jieba_next/posseg/char_state_tab.py
jieba_next/posseg/viterbi.py
jieba_next/finalseg/prob_trans.py
jieba_next/finalseg/prob_emit.py
jieba_next/finalseg/__init__.py
jieba_next/finalseg/prob_start.py
