Metadata-Version: 2.4
Name: jieba-next
Version: 1.0.0a5
Summary: Modernized fork of jieba_fast, with python 3.9+ support and Rust speedups.
Author-email: mxcoras <mxcoras@outlook.com>
License: MIT
Project-URL: Homepage, https://github.com/mxcoras/jieba-next
Project-URL: Bug Tracker, https://github.com/mxcoras/jieba-next/issues
Keywords: NLP,tokenizing
Classifier: Intended Audience :: Developers
Classifier: Operating System :: OS Independent
Classifier: Natural Language :: Chinese (Simplified)
Classifier: Natural Language :: Chinese (Traditional)
Classifier: Programming Language :: Python
Classifier: Programming Language :: Python :: 3
Classifier: Programming Language :: Python :: 3.9
Classifier: Programming Language :: Python :: 3.10
Classifier: Programming Language :: Python :: 3.11
Classifier: Programming Language :: Python :: 3.12
Classifier: Programming Language :: Python :: 3.13
Classifier: Programming Language :: Rust
Classifier: Topic :: Text Processing
Classifier: Topic :: Text Processing :: Indexing
Classifier: Topic :: Text Processing :: Linguistic
Requires-Python: >=3.9
License-File: LICENSE
Provides-Extra: analyse
Requires-Dist: whoosh; extra == "analyse"
Dynamic: license-file
